tap_clockify/__init__.py
tap_clockify/client.py
tap_clockify/schemas/__init__.py
tap_clockify/schemas/clients.py
tap_clockify/schemas/projects.py
tap_clockify/schemas/tags.py
tap_clockify/schemas/tasks.py
tap_clockify/schemas/time_entries.py
tap_clockify/schemas/users.py
tap_clockify/schemas/workspaces.py
tap_clockify/streams.py
tap_clockify/tap.py
tap_clockify/tests/__init__.py
tap_clockify/tests/test_core.py
tap_clockify-1.0.7.dist-info/entry_points.txt
tap_clockify-1.0.7.dist-info/LICENSE
tap_clockify-1.0.7.dist-info/WHEEL
tap_clockify-1.0.7.dist-info/METADATA
tap_clockify-1.0.7.dist-info/RECORD
