Metadata-Version: 2.1
Name: tap-clockify
Version: 1.0.7
Summary: Singer tap for Clockify, built with the Meltano SDK for Singer Taps.
Home-page: https://github.com/immuta/tap-clockify
License: MIT
Keywords: singer,elt,replication
Author: Stephen Bailey
Author-email: stkbailey@gmail.com
Requires-Python: >=3.6.2,<3.10
Classifier: Development Status :: 5 - Production/Stable
Classifier: License :: OSI Approved :: MIT License
Classifier: Programming Language :: Python :: 3
Classifier: Programming Language :: Python :: 3.7
Classifier: Programming Language :: Python :: 3.8
Classifier: Programming Language :: Python :: 3.9
Classifier: Programming Language :: Python :: 3 :: Only
Classifier: Topic :: Database
Requires-Dist: black (>=21.7-beta.0,<22.0)
Requires-Dist: requests (>=2.25.1,<3.0.0)
Requires-Dist: singer-sdk
Project-URL: Repository, https://github.com/immuta/tap-clockify
